anyerplint/__init__.py
anyerplint/__main__.py
anyerplint/ast.py
anyerplint/business_logic.py
anyerplint/library.py
anyerplint/preprocessor.py
anyerplint/recursive_list.py
anyerplint/tnex.py
anyerplint/translate.py
anyerplint/util.py
anyerplint/version.txt
anyerplint/cli/__init__.py
anyerplint/cli/check.py
anyerplint/cli/importcmd.py
anyerplint/cli/initcmd.py
anyerplint/cli/main.py
anyerplint/cli/parsecmd.py
anyerplint-0.3.5.dist-info/METADATA
anyerplint-0.3.5.dist-info/WHEEL
anyerplint-0.3.5.dist-info/entry_points.txt
anyerplint-0.3.5.dist-info/top_level.txt
anyerplint-0.3.5.dist-info/RECORD
